
{"operationName":"sectionProductFilters","variables":{"sectionId":386,"selectedValueIds":[313025],"excludedValueIds":[]},"query":"query sectionProductFilters($sectionId: Int!, $selectedValueIds: [Int], $excludedValueIds: [Int], $selectedMinPrice: Int, $selectedMaxPrice: Int, $searchPhrase: String) {\n  sectionProductFilters(sectionId: $sectionId, selectedValueIds: $selectedValueIds, excludedValueIds: $excludedValueIds, selectedMinPrice: $selectedMinPrice, selectedMaxPrice: $selectedMaxPrice, searchPhrase: $searchPhrase) {\n    _id\n    title\n    description\n    type\n    weight\n    values {\n      _id\n      isNoFollow\n      title\n      alias\n      description\n      weight\n      isPublic\n      productsCount\n      totalProductsCount\n      popularity\n      groupId\n      groupTitle\n      __typename\n    }\n    topValues {\n      _id\n      isNoFollow\n      title\n      alias\n      description\n      weight\n      isPublic\n      productsCount\n      totalProductsCount\n      popularity\n      groupId\n      groupTitle\n      __typename\n    }\n    valueGroups {\n      _id\n      title\n      values {\n        _id\n        title\n        alias\n        description\n        weight\n        isPublic\n        productsCount\n        totalProductsCount\n        popularity\n        groupId\n        groupTitle\n        __typename\n      }\n      __typename\n    }\n    popularity\n    isPublic\n    isWrappable\n    isExcludable\n    useValuesSearch\n    __typename\n  }\n}\n"}
